{
    "id": "M0763",
    "nome": "Módulo Cura Auto-Otimização",
    "categoria": "Cura",
    "subcategoria": "Auto-Otimização",
    "tipo_comunicacao": "SUPORTE",
    "prioridade": 85,
    "status": "ATIVO",
    "frequencia_otima": "Φ-28.1",
    "dimensoes_ativas": 4,
    "equacoes_correlacionadas": [107, 184, 88],
    "metricas": {
        "eficiencia": 0.826,
        "estabilidade": 0.886,
        "coerencia": 0.789
    },
    "timestamp_criacao": "2025-10-04T22:53:53+00:00",
    "ultima_atividade": "2025-10-04T22:53:53+00:00"
}
