{
    "id": "M0046",
    "nome": "Módulo Fractal Coerência",
    "categoria": "Fractal",
    "subcategoria": "Coerência",
    "tipo_comunicacao": "SUPORTE",
    "prioridade": 67,
    "status": "ATIVO",
    "frequencia_otima": "Φ-27.1",
    "dimensoes_ativas": 4,
    "equacoes_correlacionadas": [169, 150, 38],
    "metricas": {
        "eficiencia": 0.868,
        "estabilidade": 0.887,
        "coerencia": 0.807
    },
    "timestamp_criacao": "2025-10-04T22:53:30+00:00",
    "ultima_atividade": "2025-10-04T22:53:30+00:00"
}
