{
    "id": "M0660",
    "nome": "Módulo Cura Sincronização",
    "categoria": "Cura",
    "subcategoria": "Sincronização",
    "tipo_comunicacao": "SUPORTE",
    "prioridade": 34,
    "status": "ATIVO",
    "frequencia_otima": "Φ-33.0",
    "dimensoes_ativas": 1,
    "equacoes_correlacionadas": [132, 87, 189],
    "metricas": {
        "eficiencia": 0.985,
        "estabilidade": 0.891,
        "coerencia": 0.879
    },
    "timestamp_criacao": "2025-10-04T22:53:50+00:00",
    "ultima_atividade": "2025-10-04T22:53:50+00:00"
}
