{
    "id": "M0092",
    "nome": "Módulo Quântico Auto-Otimização",
    "categoria": "Quântico",
    "subcategoria": "Auto-Otimização",
    "tipo_comunicacao": "SUPORTE",
    "prioridade": 47,
    "status": "ATIVO",
    "frequencia_otima": "Φ-29.1",
    "dimensoes_ativas": 8,
    "equacoes_correlacionadas": [57, 185, 131],
    "metricas": {
        "eficiencia": 0.874,
        "estabilidade": 0.790,
        "coerencia": 0.984
    },
    "timestamp_criacao": "2025-10-04T22:53:31+00:00",
    "ultima_atividade": "2025-10-04T22:53:31+00:00"
}
