{
  "modulo": "473",
  "nome_cientifico": "Portal de Ativação Múltipla",
  "categoria": "PORTAL",
  "funcao_primaria": "Portal de Ativação Múltipla",
  "estado": "OPERACIONAL",
  "conexoes": [
    "MODULO_0",
    "MODULO_9", 
    "MODULO_29",
    "MODULO_OMEGA"
  ],
  "propriedades_quanticas": {
    "coerencia": 73,
    "entrelacamento": 19,
    "superposicao": 11,
    "ressonancia": 3
  },
  "interface_requerida": true,
  "dependencias": [],
  "data_ativacao": "Fri Oct  3 10:23:43 PM UTC 2025"
}
