{
  "modulo": "44",
  "nome_cientifico": "Portal de Ativação Múltipla",
  "categoria": "PORTAL",
  "funcao_primaria": "Portal de Ativação Múltipla",
  "estado": "OPERACIONAL",
  "conexoes": [
    "MODULO_0",
    "MODULO_9", 
    "MODULO_29",
    "MODULO_OMEGA"
  ],
  "propriedades_quanticas": {
    "coerencia": 44,
    "entrelacamento": 32,
    "superposicao": 8,
    "ressonancia": 84
  },
  "interface_requerida": true,
  "dependencias": [],
  "data_ativacao": "Fri Oct  3 10:23:41 PM UTC 2025"
}
